mobile_mcp/__init__.py
mobile_mcp/config.py
mobile_mcp/core/__init__.py
mobile_mcp/core/basic_tools_lite.py
mobile_mcp/core/device_manager.py
mobile_mcp/core/dynamic_config.py
mobile_mcp/core/ios_client_wda.py
mobile_mcp/core/ios_device_manager_wda.py
mobile_mcp/core/mobile_client.py
mobile_mcp/core/template_matcher.py
mobile_mcp/core/templates/close_buttons/auto_x_0112_151217.png
mobile_mcp/core/templates/close_buttons/auto_x_0112_152037.png
mobile_mcp/core/templates/close_buttons/auto_x_0112_152840.png
mobile_mcp/core/templates/close_buttons/auto_x_0112_153256.png
mobile_mcp/core/templates/close_buttons/auto_x_0112_154847.png
mobile_mcp/core/templates/close_buttons/gray_x_stock_ad.png
mobile_mcp/core/utils/__init__.py
mobile_mcp/core/utils/logger.py
mobile_mcp/core/utils/operation_history_manager.py
mobile_mcp/core/utils/smart_wait.py
mobile_mcp/mcp_tools/__init__.py
mobile_mcp/mcp_tools/mcp_server.py
mobile_mcp/utils/__init__.py
mobile_mcp/utils/logger.py
mobile_mcp/utils/xml_formatter.py
mobile_mcp/utils/xml_parser.py
mobile_mcp_ai-2.6.3.dist-info/licenses/LICENSE
mobile_mcp_ai-2.6.3.dist-info/METADATA
mobile_mcp_ai-2.6.3.dist-info/WHEEL
mobile_mcp_ai-2.6.3.dist-info/entry_points.txt
mobile_mcp_ai-2.6.3.dist-info/top_level.txt
mobile_mcp_ai-2.6.3.dist-info/RECORD
