Metadata-Version: 2.4
Name: mobile-mcp-ai
Version: 2.6.3
Summary: 移动端自动化 MCP Server - 支持 Android/iOS，AI 功能可选（基础工具不需要 AI）
Home-page: https://github.com/test111ddff-hash/mobile-mcp-ai
Author: douzi
Author-email: 1492994674@qq.com
Project-URL: Documentation, https://github.com/test111ddff-hash/mobile-mcp-ai
Project-URL: Source, https://github.com/test111ddff-hash/mobile-mcp-ai
Project-URL: Tracker, https://github.com/test111ddff-hash/mobile-mcp-ai/issues
Keywords: mobile,automation,testing,android,ios,mcp,ai,pytest,cursor
Classifier: Development Status :: 4 - Beta
Classifier: Intended Audience :: Developers
Classifier: License :: OSI Approved :: Apache Software License
Classifier: Programming Language :: Python :: 3
Classifier: Programming Language :: Python :: 3.8
Classifier: Programming Language :: Python :: 3.9
Classifier: Programming Language :: Python :: 3.10
Classifier: Programming Language :: Python :: 3.11
Classifier: Topic :: Software Development :: Testing
Classifier: Topic :: Software Development :: Libraries :: Python Modules
Requires-Python: >=3.8
License-File: LICENSE
Requires-Dist: uiautomator2>=2.16.0
Requires-Dist: adbutils>=1.2.0
Requires-Dist: Pillow>=10.0.0
Requires-Dist: mcp>=0.9.0
Requires-Dist: python-dotenv>=1.0.0
Provides-Extra: ai
Requires-Dist: dashscope>=1.10.0; extra == "ai"
Requires-Dist: openai>=1.0.0; extra == "ai"
Requires-Dist: anthropic>=0.3.0; extra == "ai"
Provides-Extra: test
Requires-Dist: pytest>=8.0.0; extra == "test"
Requires-Dist: pytest-asyncio>=0.21.0; extra == "test"
Requires-Dist: allure-pytest>=2.13.0; extra == "test"
Provides-Extra: dev
Requires-Dist: pytest>=8.0.0; extra == "dev"
Requires-Dist: pytest-asyncio>=0.21.0; extra == "dev"
Requires-Dist: twine>=4.0.0; extra == "dev"
Requires-Dist: build>=0.10.0; extra == "dev"
Provides-Extra: ios
Requires-Dist: tidevice>=0.11.0; extra == "ios"
Requires-Dist: facebook-wda>=1.4.0; extra == "ios"
Provides-Extra: h5
Requires-Dist: Appium-Python-Client>=3.0.0; extra == "h5"
Requires-Dist: selenium>=4.0.0; extra == "h5"
Provides-Extra: all
Requires-Dist: dashscope>=1.10.0; extra == "all"
Requires-Dist: openai>=1.0.0; extra == "all"
Requires-Dist: anthropic>=0.3.0; extra == "all"
Requires-Dist: Appium-Python-Client>=3.0.0; extra == "all"
Requires-Dist: selenium>=4.0.0; extra == "all"
Requires-Dist: pytest>=8.0.0; extra == "all"
Requires-Dist: pytest-asyncio>=0.21.0; extra == "all"
Requires-Dist: allure-pytest>=2.13.0; extra == "all"
Dynamic: author
Dynamic: author-email
Dynamic: classifier
Dynamic: description
Dynamic: description-content-type
Dynamic: home-page
Dynamic: keywords
Dynamic: license-file
Dynamic: project-url
Dynamic: provides-extra
Dynamic: requires-dist
Dynamic: requires-python
Dynamic: summary
